test_datasets_1/__init__.py
test_datasets_1/dataloaders.py
test_datasets_1/utils.py
test_datasets_1/data/__init__.py
test_datasets_1/data/ACSF1/ACSF1_TEST.tsv
test_datasets_1/data/ACSF1/ACSF1_TRAIN.tsv
test_datasets_1/data/ACSF1/__init__.py
test_datasets_1/data/Adiac/Adiac_TEST.tsv
test_datasets_1/data/Adiac/Adiac_TRAIN.tsv
test_datasets_1/data/Adiac/__init__.py
test_datasets_1/data/AllGestureWiimoteX/AllGestureWiimoteX_TEST.tsv
test_datasets_1/data/AllGestureWiimoteX/AllGestureWiimoteX_TRAIN.tsv
test_datasets_1/data/AllGestureWiimoteX/__init__.py
test_datasets_1/data/AllGestureWiimoteY/AllGestureWiimoteY_TEST.tsv
test_datasets_1/data/AllGestureWiimoteY/AllGestureWiimoteY_TRAIN.tsv
test_datasets_1/data/AllGestureWiimoteY/__init__.py
test_datasets_1/data/AllGestureWiimoteZ/AllGestureWiimoteZ_TEST.tsv
test_datasets_1/data/AllGestureWiimoteZ/AllGestureWiimoteZ_TRAIN.tsv
test_datasets_1/data/AllGestureWiimoteZ/__init__.py
test_datasets_1/data/ArrowHead/ArrowHead_TEST.tsv
test_datasets_1/data/ArrowHead/ArrowHead_TRAIN.tsv
test_datasets_1/data/ArrowHead/__init__.py
test_datasets_1/data/BME/BME_TEST.tsv
test_datasets_1/data/BME/BME_TRAIN.tsv
test_datasets_1/data/BME/__init__.py
test_datasets_1/data/Beef/Beef_TEST.tsv
test_datasets_1/data/Beef/Beef_TRAIN.tsv
test_datasets_1/data/Beef/__init__.py
test_datasets_1/data/BeetleFly/BeetleFly_TEST.tsv
test_datasets_1/data/BeetleFly/BeetleFly_TRAIN.tsv
test_datasets_1/data/BeetleFly/__init__.py
test_datasets_1/data/BirdChicken/BirdChicken_TEST.tsv
test_datasets_1/data/BirdChicken/BirdChicken_TRAIN.tsv
test_datasets_1/data/BirdChicken/__init__.py
test_datasets_1/data/CBF/CBF_TEST.tsv
test_datasets_1/data/CBF/CBF_TRAIN.tsv
test_datasets_1/data/CBF/__init__.py
test_datasets_1/data/Car/Car_TEST.tsv
test_datasets_1/data/Car/Car_TRAIN.tsv
test_datasets_1/data/Car/__init__.py
test_datasets_1/data/Chinatown/Chinatown_TEST.tsv
test_datasets_1/data/Chinatown/Chinatown_TRAIN.tsv
test_datasets_1/data/Chinatown/__init__.py
test_datasets_1-0.0.24.dist-info/METADATA
test_datasets_1-0.0.24.dist-info/WHEEL
test_datasets_1-0.0.24.dist-info/top_level.txt
test_datasets_1-0.0.24.dist-info/RECORD
